adobase/__init__.py
adobase/__main__.py
adobase/defaults.json
adobase/defaults.py
adobase/level.py
adobase/params.py
adobase/utils.py
adobase/__pycache__/__init__.cpython-313.pyc
adobase/__pycache__/constants.cpython-313.pyc
adobase/__pycache__/defaults.cpython-313.pyc
adobase/__pycache__/level.cpython-313.pyc
adobase/__pycache__/params.cpython-313.pyc
adobase/__pycache__/utils.cpython-313.pyc
adobase/tests/test_decoration.py
adobase/tests/test_event.py
adobase/tests/test_level.py
adobase/tests/test_level_info.py
adobase/tests/__pycache__/test_level.cpython-313.pyc
adobase-1.0.0.dist-info/METADATA
adobase-1.0.0.dist-info/WHEEL
adobase-1.0.0.dist-info/top_level.txt
adobase-1.0.0.dist-info/RECORD
