Metadata-Version: 2.4
Name: ADOBase
Version: 1.0.0
Summary: 为 ADOFAI 游戏的 .adofai 关卡文件提供读写、查找、增删改等操作的库
Home-page: https://github.com/small-lizi/ADOBase
Author: memsys-lizi
Author-email: memsys-lizi <your_email@example.com>
License: MIT
Keywords: adofai,level,json,game,parser
Classifier: Programming Language :: Python :: 3
Classifier: License :: OSI Approved :: MIT License
Classifier: Operating System :: OS Independent
Classifier: Intended Audience :: Developers
Classifier: Topic :: Software Development :: Libraries :: Python Modules
Requires-Python: >=3.7
Dynamic: author
Dynamic: home-page
Dynamic: requires-python
